pretix_matrix_inviter/__init__.py
pretix_matrix_inviter/apps.py
pretix_matrix_inviter/forms.py
pretix_matrix_inviter/helpers.py
pretix_matrix_inviter/signals.py
pretix_matrix_inviter/tasks.py
pretix_matrix_inviter/urls.py
pretix_matrix_inviter/views.py
pretix_matrix_inviter/locale/django.pot
pretix_matrix_inviter/locale/de/LC_MESSAGES/django.mo
pretix_matrix_inviter/locale/de/LC_MESSAGES/django.po
pretix_matrix_inviter/locale/de_Informal/.gitkeep
pretix_matrix_inviter/locale/de_Informal/LC_MESSAGES/django.mo
pretix_matrix_inviter/locale/de_Informal/LC_MESSAGES/django.po
pretix_matrix_inviter/locale/fr/LC_MESSAGES/django.mo
pretix_matrix_inviter/locale/fr/LC_MESSAGES/django.po
pretix_matrix_inviter/static/pretix_matrix_inviter/.gitkeep
pretix_matrix_inviter/templates/pretix_matrix_inviter/.gitkeep
pretix_matrix_inviter/templates/pretix_matrix_inviter/settings.html
pretix_matrix_inviter-1.8.0.dist-info/licenses/LICENSE
pretix_matrix_inviter-1.8.0.dist-info/METADATA
pretix_matrix_inviter-1.8.0.dist-info/WHEEL
pretix_matrix_inviter-1.8.0.dist-info/entry_points.txt
pretix_matrix_inviter-1.8.0.dist-info/top_level.txt
pretix_matrix_inviter-1.8.0.dist-info/RECORD
