Metadata-Version: 2.4
Name: pretix-matrix-inviter
Version: 1.8.0
Summary: Invite pretix participants to a Matrix Room or Space.
Author-email: Felix Schäfer <admin@kif.rocks>
Maintainer-email: Felix Schäfer <admin@kif.rocks>
License: MIT License
Project-URL: Homepage, https://gitlab.fachschaften.org/kif/pretix-matrix-inviter
Project-URL: Repository, https://gitlab.fachschaften.org/kif/pretix-matrix-inviter
Project-URL: Changelog, https://gitlab.fachschaften.org/kif/pretix-matrix-inviter/-/blob/main/CHANGELOG.md
Project-URL: Tracker, https://gitlab.fachschaften.org/kif/pretix-matrix-inviter/-/issues
Project-URL: pretix Marketplace, https://marketplace.pretix.eu/products/pretix-matrix-inviter/
Keywords: pretix,matrix
Classifier: Development Status :: 5 - Production/Stable
Classifier: Framework :: Django
Classifier: License :: OSI Approved :: MIT License
Classifier: Topic :: Communications :: Chat
License-File: LICENSE
Requires-Dist: requests
Dynamic: license-file
